README.md
setup.py
aio_ormsql/__init__.py
aio_ormsql/classes.py
aio_ormsql/db.py
aio_ormsql.egg-info/PKG-INFO
aio_ormsql.egg-info/SOURCES.txt
aio_ormsql.egg-info/dependency_links.txt
aio_ormsql.egg-info/requires.txt
aio_ormsql.egg-info/top_level.txt