Metadata-Version: 2.1
Name: aio-ormsql
Version: 0.0.5
Summary: Simple asynchronous MySQL ORM class.
Home-page: https://github.com/TheDevFromKer/aio_ormsql
Author: TheDevFromKer
License: GNU 3.0
Keywords: python mysql,async mysql python,mysql python,python async orm,async orm,mysql async orm
Platform: UNKNOWN
Classifier: Programming Language :: Python :: 3.6
Classifier: Programming Language :: Python :: 3.7
Classifier: Operating System :: OS Independent
